<?xml version="1.0" encoding="utf-8"?>
<ModMetaData>
  <name>Level Up!</name>
  <author>krafs</author>
  <packageId>Krafs.LevelUp</packageId>
  <modVersion>5.2.0</modVersion>
  <description>Level up notifications!</description>
  <url>https://github.com/krafs/LevelUp</url>
  <modIconPath>LevelUp/Icon</modIconPath>
  <supportedVersions>
    <li>1.6</li>
  </supportedVersions>
  <modDependencies>
    <li>
      <packageId>brrainz.harmony</packageId>
      <displayName>Harmony</displayName>
      <downloadUrl>https://github.com/pardeike/HarmonyRimWorld/releases/latest</downloadUrl>
      <steamWorkshopUrl>steam://url/CommunityFilePage/2009463077</steamWorkshopUrl>
    </li>
  </modDependencies>
</ModMetaData>
